clewareADC/__init__.py
clewareADC/clewareADC.py
clewareADC-0.2.dist-info/METADATA
clewareADC-0.2.dist-info/RECORD
clewareADC-0.2.dist-info/WHEEL
clewareADC-0.2.dist-info/top_level.txt
