Metadata-Version: 2.1
Name: clewareADC
Version: 0.2
Summary: Python module to read values from Cleware USB-ADC 2
Home-page: https://gitlab.com/darkforce/clewareADC
Author: Johannes Koch
Author-email: johannes@ortsraum.de
License: MIT
Download-URL: https://gitlab.com/darkforce/clewareADC/-/archive/0.2/clewareADC-0.2.tar.gz
Keywords: cleware,adc,hidapi
Platform: UNKNOWN
Classifier: Development Status :: 5 - Production/Stable
Classifier: Intended Audience :: Science/Research
Classifier: Intended Audience :: Developers
Classifier: License :: OSI Approved :: MIT License
Classifier: Programming Language :: Python
Classifier: Topic :: Home Automation
Classifier: Topic :: Scientific/Engineering
Requires-Dist: hidapi
